<includes>
	<include name="BehindDialogFadeOut">
		<control type="image">
			<posx>0</posx>
			<posy>0</posy>
			<width>1280</width>
			<height>720</height>
			<texture>black-back.png</texture>
			<animation effect="fade" time="400">Visible</animation>
			<animation effect="fade" time="200">Hidden</animation>
			<visible>Window.IsActive(MovieInformation) | Window.IsActive(MusicInformation) | Window.IsActive(SongInformation) | Window.IsActive(FileBrowser) | Window.IsActive(TextViewer) | Window.IsActive(AddonSettings) | Window.IsActive(ContentSettings) | Window.IsActive(SelectDialog) | Window.IsActive(FileStackingDialog) | Window.IsActive(MediaSource) | Window.IsActive(PictureInfo) | Window.IsActive(PlayerControls) | Window.IsActive(VirtualKeyboard) | Window.IsActive(NumericInput) | Window.IsActive(ProfileSettings) | Window.IsActive(LockSettings) | Window.IsActive(SmartPlaylistEditor) | Window.IsActive(SmartPlaylistRule) | Window.IsActive(script-Apple_Movie_Trailers-settings.xml) | Window.IsActive(script-Apple_Movie_Trailers-chooser.xml) | Window.IsActive(script-Apple_Movie_Trailers-search.xml) | Window.IsActive(script-Apple_Movie_Trailers-showtimes.xml) | Window.IsActive(script-XBMC_Lyrics-settings.xml) | Window.IsActive(script-RSS_Editor-rssEditor.xml) | Window.IsActive(script-RSS_Editor-setEditor.xml) | Window.IsActive(AddonInformation)</visible>
		</control>
	</include>
	<include name="IncludeTest">
	    <control type="label">
	        <description>date/time label</description>
	        <posx>0</posx>
	        <posy>65</posy>
	        <width>450</width>
	        <height>35</height>
	        <align>right</align>
	        <aligny>center</aligny>
	        <font>font12</font>
	        <textcolor>ffffffff</textcolor>
	        <label>TestInclude</label>
	    </control>
	</include>
</includes>
